{
  "parent": "rajswordmod:item/deflect_sword",
  "gui_light": "front",
  "textures": {
    "layer0": "rajswordmod:item/deflect_sword_upgraded"
  },
  "display": {
    "firstperson_righthand": {
      "rotation": [ -15, 180, 0 ],
      "translation": [ -4, 4, -0 ],
      "scale": [ 0.88, 0.88, 0.88 ]
    },
    "firstperson_lefthand": {
      "rotation": [ -15, 0, 0 ],
      "translation": [ -4, 4, -0 ],
      "scale": [ 0.88, 0.88, 0.88 ]
    },
    "ground": {
      "translation": [0, 3, 0],
      "rotation": [0, 0, 0],
      "scale": [0.65, 0.65, 0.65]
    },
  "gui": {
    "translation": [1, 1, 0],
    "scale": [1.2, 1.2, 1.2]
    },
    "fixed": {
      "translation": [0, 0, 0],
      "scale": [1.2, 1.2, 1.2]
    }
  }
}